MANIFEST.in
README.rst
bootstrap.py
buildout.cfg
setup.cfg
setup.py
collective/__init__.py
collective.stats.egg-info/PKG-INFO
collective.stats.egg-info/SOURCES.txt
collective.stats.egg-info/dependency_links.txt
collective.stats.egg-info/entry_points.txt
collective.stats.egg-info/namespace_packages.txt
collective.stats.egg-info/not-zip-safe
collective.stats.egg-info/requires.txt
collective.stats.egg-info/top_level.txt
collective/stats/__init__.py
collective/stats/configure.zcml
collective/stats/export.py
collective/stats/pubtime.py
collective/stats/transchain.py
collective/stats/zodbstats.py
docs/HISTORY.txt
docs/INSTALL.txt
docs/LICENSE.ZPL