Metadata-Version: 2.1
Name: collective.stats
Version: 1.1.0
Summary: Zope low level stats per request.
Home-page: http://github.com/collective/collective.stats
Author: Enfold Systems
Author-email: contact@enfoldsystems.com
Maintainer: Alex Clark
Maintainer-email: aclark@aclark.net
License: ZPL
Keywords: collective stats plone zope
Platform: UNKNOWN
Classifier: Environment :: Console
Classifier: Framework :: Plone
Classifier: Framework :: Plone :: 5.2
Classifier: Framework :: Plone :: 6.0
Classifier: Framework :: Zope2
Classifier: Intended Audience :: Developers
Classifier: Intended Audience :: System Administrators
Classifier: License :: OSI Approved :: Zope Public License
Classifier: Operating System :: OS Independent
Classifier: Topic :: Software Development :: Libraries :: Python Modules
Classifier: Topic :: System :: Logging
Classifier: Programming Language :: Python
Classifier: Programming Language :: Python :: 2
Classifier: Programming Language :: Python :: 2.7
Classifier: Programming Language :: Python :: 3
Classifier: Programming Language :: Python :: 3.5
Classifier: Programming Language :: Python :: 3.6
Classifier: Programming Language :: Python :: 3.7
Classifier: Programming Language :: Python :: 3.8
Classifier: Programming Language :: Python :: Implementation :: CPython
Classifier: Development Status :: 5 - Production/Stable
Provides-Extra: oldzope
